README.rst
setup.py
pynewtonmath/__init__.py
pynewtonmath/core.py
pynewtonmath/wrapper.py
pynewtonmath.egg-info/PKG-INFO
pynewtonmath.egg-info/SOURCES.txt
pynewtonmath.egg-info/dependency_links.txt
pynewtonmath.egg-info/not-zip-safe
pynewtonmath.egg-info/top_level.txt